junmook_bmi_test/bmi_test.py
junmook_bmi_test-0.0.0.2.dist-info/METADATA
junmook_bmi_test-0.0.0.2.dist-info/WHEEL
junmook_bmi_test-0.0.0.2.dist-info/top_level.txt
junmook_bmi_test-0.0.0.2.dist-info/RECORD
