Metadata-Version: 2.1
Name: junmook-bmi-test
Version: 0.0.0.2
Summary: My Second Test Package
Home-page: https://google.com
Author: Junmook Oh
Author-email: ohjun062@gmail.com
License: MIT
Platform: UNKNOWN
Requires-Python: >=3
